modelhub/__init__.py
modelhub/start.py
modelhub_ai-0.0.6.dist-info/LICENSE
modelhub_ai-0.0.6.dist-info/METADATA
modelhub_ai-0.0.6.dist-info/WHEEL
modelhub_ai-0.0.6.dist-info/entry_points.txt
modelhub_ai-0.0.6.dist-info/top_level.txt
modelhub_ai-0.0.6.dist-info/RECORD
