Metadata-Version: 2.1
Name: modelhub-ai
Version: 0.0.6
Summary: UNKNOWN
Home-page: https://github.com/modelhub-ai/modelhub
Author: Ahmed Hosny
Author-email: info@modelhub.ai
License: MIT
Keywords: ai modelhub harvard dana-farber brigham deep learning open science
Platform: UNKNOWN
Classifier: Programming Language :: Python :: 3
Classifier: License :: OSI Approved :: MIT License
Classifier: Operating System :: OS Independent
